musicflower/__init__.py
musicflower/__main__.py
musicflower/features.py
musicflower/istarmap.py
musicflower/loader.py
musicflower/plotting.py
musicflower/util.py
musicflower/visualisers.py
musicflower/webapp.py
musicflower/assets/favicon.ico
musicflower/assets/fontawesome-free-5.15.4-web/css/fontawesome.css
musicflower/assets/fontawesome-free-5.15.4-web/css/fontawesome.min.css
musicflower/assets/fontawesome-free-5.15.4-web/css/solid.css
musicflower/assets/fontawesome-free-5.15.4-web/css/solid.min.css
musicflower/assets/fontawesome-free-5.15.4-web/webfonts/fa-solid-900.eot
musicflower/assets/fontawesome-free-5.15.4-web/webfonts/fa-solid-900.svg
musicflower/assets/fontawesome-free-5.15.4-web/webfonts/fa-solid-900.ttf
musicflower/assets/fontawesome-free-5.15.4-web/webfonts/fa-solid-900.woff
musicflower/assets/fontawesome-free-5.15.4-web/webfonts/fa-solid-900.woff2
musicflower-0.1.0.dist-info/licenses/LICENSE
musicflower-0.1.0.dist-info/METADATA
musicflower-0.1.0.dist-info/WHEEL
musicflower-0.1.0.dist-info/top_level.txt
musicflower-0.1.0.dist-info/RECORD
