Metadata-Version: 2.4
Name: musicflower
Version: 0.1.0
Home-page: https://github.com/robert-lieck/musicflower
Author: Robert Lieck
Author-email: robert.lieck@durham.ac.uk
Classifier: Programming Language :: Python :: 3
Classifier: License :: OSI Approved :: GNU General Public License v3 (GPLv3)
Classifier: Operating System :: OS Independent
Requires-Python: >=3.9
License-File: LICENSE
Requires-Dist: numpy
Requires-Dist: tqdm
Requires-Dist: scipy
Requires-Dist: librosa
Requires-Dist: plotly
Requires-Dist: kaleido
Requires-Dist: pandas
Requires-Dist: dash
Requires-Dist: dash-bootstrap-components
Requires-Dist: matplotlib
Requires-Dist: triangularmap>=0.1.0
Requires-Dist: pitchscapes
Requires-Dist: pitchtypes
Dynamic: author
Dynamic: author-email
Dynamic: classifier
Dynamic: description
Dynamic: description-content-type
Dynamic: home-page
Dynamic: license-file
Dynamic: requires-dist
Dynamic: requires-python
